{
    "Froge": {
        "location": "Jungle Perimeter",
        "baseExp": "2",
        "baseShinyRate": "5%",
        "shiny": "Poison Froge",
        "effForBonus": "35"
    },
    "Crabbo": {
        "location": "Salty Shores",
        "baseExp": "8",
        "baseShinyRate": "3%",
        "shiny": "Mutant Crabbo",
        "effForBonus": "400"
    },
    "Scorpie": {
        "location": "The Ring",
        "baseExp": "25",
        "baseShinyRate": "2%",
        "shiny": "Crescent Scorpie",
        "effForBonus": "1500"
    },
    "Mousey": {
        "location": "Rats Nest",
        "baseExp": "50",
        "baseShinyRate": "1%",
        "shiny": "Nakeo Moleo",
        "effForBonus": "3500"
    },
    "Owlio": {
        "location": "Hollowed Trunk",
        "baseExp": "80",
        "baseShinyRate": "0.6%",
        "shiny": "Minervowl",
        "effForBonus": "8000"
    },
    "Pingy": {
        "location": "The Stache Split",
        "baseExp": "125",
        "baseShinyRate": "0.3%",
        "shiny": "Eternal Lord of The Undying Ember",
        "effForBonus": "15000"
    },
    "Bunny": {
        "location": "Thermonuclear Climb",
        "baseExp": "160",
        "baseShinyRate": "0.15%",
        "shiny": "Purbunni",
        "effForBonus": "45000"
    },
    "Dung Beat": {
        "location": "Efaunt's Tomb",
        "baseExp": "200",
        "baseShinyRate": "0.06%",
        "shiny": "Jade Scarab",
        "effForBonus": "100000"
    },
    "Honker": {
        "location": "Wam Wonderland",
        "baseExp": "250",
        "baseShinyRate": "0.02%",
        "shiny": "Diamond Duck",
        "effForBonus": "200000"
    }
}